<?xml version="1.0" encoding="UTF-8"?>
<locales>

    <groups name="pcsg/grouppasswordmanager" datatype="php">

        <!-- Class: Manager -->
        <locale name="exception.manager.create.password.missing.title.description">
            <de><![CDATA[Der Passwort-Eintrag konnte nicht erstellt werden. Ein Passwort-Eintrag benötigt einen Titel und eine Kurzbeschreibung.]]></de>
        </locale>

        <!-- Class: Password -->
        <locale name="exception.password.not.found">
            <de><![CDATA[Das Passwort mit der ID [passwordId] wurde nicht gefunden.]]></de>
        </locale>
        <locale name="exception.password.decryption.error">
            <de><![CDATA[Das Passwort mit der ID [passwordId] konnte nicht erfolgreich entschlüsselt werden.]]></de>
        </locale>
        <locale name="exception.password.payload.wrong.datatype">
            <de><![CDATA[Die Nutzdaten für das Passwort mit der ID [passwordId] konnte nicht gesetzt werden.]]></de>
        </locale>
        <locale name="exception.password.addviewuser.no.rights">
            <de><![CDATA[Sie können Benutzern für das Passwort mit der ID [passwordId] keine Ansichtsrechte zuweisen, weil Sie dazu nicht die nötigen Rechte haben.]]></de>
        </locale>
        <locale name="exception.password.addviewuser.error">
            <de><![CDATA[Beim Hinzufügen des Ansichtsrechts für das Passwort mit der ID [passwordId] für Benutzer mit der ID [userId] ist ein unerwarteter Fehler aufgetreten. Bitte wenden Sie sich an einen Administrator.]]></de>
        </locale>
        <locale name="exception.password.removviewtuser.no.rights">
            <de><![CDATA[Sie können Benutzern für das Passwort mit der ID [passwordId] keine Ansichtsrechte entziehen, weil Sie dazu nicht die nötigen Rechte haben.]]></de>
        </locale>
        <locale name="exception.password.removviewtuser.no.user">
            <de><![CDATA[Sie können dem Benutzer mit der ID [userId] für das Passwort mit der ID [passwordId] keine Ansichtsrechte entziehen, weil dieser das Recht nicht besitzt.]]></de>
        </locale>
        <locale name="exception.password.removviewtuser.error">
            <de><![CDATA[Beim Enziehen des Ansichtsrechts für Benutzer mit der ID [userId] für das Passwort mit der ID [passwordId] ist ein unerwarteter Fehler aufgetreten. Bitte wenden Sie sich an einen Administrator.]]></de>
        </locale>
        <locale name="exception.password.addedituser.no.rights">
            <de><![CDATA[Sie können Benutzern für das Passwort mit der ID [passwordId] keine Bearbeitungsrechte zuweisen, weil Sie dazu nicht die nötigen Rechte haben.]]></de>
        </locale>
        <locale name="exception.password.removeedituser.no.rights">
            <de><![CDATA[Sie können Benutzern für das Passwort mit der ID [passwordId] keine Bearbeitungsrechte entziehen, weil Sie dazu nicht die nötigen Rechte haben.]]></de>
        </locale>
        <locale name="exception.password.removeedituser.no.user">
            <de><![CDATA[Sie können dem Benutzer mit der ID [userId] für das Passwort mit der ID [passwordId] keine Bearbeitungsrechte entziehen, weil dieser das Recht nicht besitzt.]]></de>
        </locale>
        <locale name="exception.password.save.error">
            <de><![CDATA[Das Password mit der ID [passwordId] konnte nicht gespeichert werden. Bitte wenden Sie sich an einen Administrator.]]></de>
        </locale>
        <locale name="exception.password.delete.no.rights">
            <de><![CDATA[Sie haben nicht die nötigen Rechte, um das Passwort mit der ID [passwordId] zu löschen.]]></de>
        </locale>
        <locale name="exception.password.delete.error">
            <de><![CDATA[Beim Löschen des Passworts mit der ID [passwordId] ist ein unerwarteter Fehler aufgetreten. Bitte kontaktieren Sie einen Administrator.]]></de>
        </locale>
        <locale name="exception.password.setowner.no.rights">
            <de><![CDATA[Sie haben nicht die nötigen Rechte, um den Besitzer für das Passwort mit der ID [passwordId] zu setzen.]]></de>
        </locale>
        <locale name="error.password.create.no.security.class">
            <de><![CDATA[Sie müssen eine Sicherheitsklasse festlegen, bevor diese Operation ausgeführt werden kann.]]></de>
        </locale>
        <locale name="exception.password.create.general.error">
            <de><![CDATA[Es ist ein unerwarteter Fehler aufgetreten. Bitte kontaktieren Sie einen Administrator.]]></de>
        </locale>
        <locale name="exception.password.user.not.authenticated">
            <de><![CDATA[Der Benutzer #[userId] ist nicht für die Sicherheitsklasse des Passworts #[id] authentifiziert.]]></de>
        </locale>
        <locale name="exception.password.access.data.not.found">
            <de><![CDATA[Es wurden keine Daten für den Zugriff auf das Passwort #[id] für den Benutzer #[userId] gefunden.]]></de>
        </locale>
        <locale name="exception.password.not.authentic">
            <de><![CDATA[Das Passwort #[passwordId] hat die Authentizitätsprüfung nicht bestanden und kann daher nicht verwendet werden. Bitte wenden Sie sich an einen Administrator.]]></de>
        </locale>
        <locale name="exception.password.acces.data.decryption.fail">
            <de><![CDATA[Das Password #[passwordId] konnte nicht erfolgreich entschlüsselt werden. Der Zugriff wurde verweigert.]]></de>
        </locale>
        <locale name="exception.password.permission.denied">
            <de><![CDATA[Sie haben nicht die benötigte Berechtigung, um diese Passwort-Operation auszuführen.]]></de>
        </locale>
        <locale name="exception.password.delete.error">
            <de><![CDATA[Beim Löschen des Passworts #[passwordId] ist ein unerwarteter Fehler aufgetreten. Bitte kontaktieren Sie einen Administrator.]]></de>
        </locale>
        <locale name="exception.password.change.owner.group.to.user">
            <de><![CDATA[Der Eigentümer eines Passworts kann nicht von einer Gruppe auf einen einzelnen Benutzer gewechselt werden.]]></de>
        </locale>
        <locale name="exception.password.remove.access.cannot.remove.owner">
            <de><![CDATA[Der Passwort-Zugriff kann nicht gelöscht werden: Der Benutzer ist Eigentümer des Passworts oder gehört zur Gruppe, die Eigentümer des Passworts ist.]]></de>
        </locale>
        <locale name="exception.password.create.access.cannot.create.owner.access">
            <de><![CDATA[Der Passwort-Zugriff kann nicht für einen Benutzer erstellt werden, der Eigentümer des Passworts ist oder zur Gruppe gehört, die Eigentümer des Passworts ist.]]></de>
        </locale>
        <locale name="exception.password.create.access.user.not.eligible">
            <de><![CDATA[Der Passwort-Zugriff für Benutzer [userName] (#[userId]) kann nicht erstellt werden, da er nicht für alle Authentifizierungs-Module der Sicherheitsklasse "[securityClassTitle]" (#[securityClassId) registriert ist.]]></de>
        </locale>
        <locale name="exception.password.create.access.group.not.eligible">
            <de><![CDATA[Der Passwort-Zugriff für Benutzer der Gruppe [groupName] (#[groupId]) kann nicht erstellt werden, da nicht alle Benutzer der Gruppe für alle Authentifizierungs-Module der Sicherheitsklasse "[securityClassTitle]" (#[securityClassId) registriert ist.]]></de>
        </locale>
        <locale name="exception.password.group.password.key.not.authentic">
            <de><![CDATA[Der Entschlüsselungsschlüssel der Gruppe #[groupId] für das Password #[passwordId] hat die Authentizitätsprüfung nicht bestanden und kann daher nicht verwendet werden. Bitte wenden Sie sich an einen Administrator.]]></de>
        </locale>
        <locale name="exception.password.change.owner.user.error">
            <de><![CDATA[Der Eigentümer des Passworts #[passwordId] konnte nicht auf den Benutzer #[newOwnerId] geändert werden, da ein unerwarteter Fehler aufgetreten ist. Bitte wenden Sie sich an einen Administrator.]]></de>
        </locale>
        <locale name="exception.password.change.owner.group.error">
            <de><![CDATA[Der Eigentümer des Passworts #[passwordId] konnte nicht auf die Gruppe #[newOwnerId] geändert werden, da ein unerwarteter Fehler aufgetreten ist. Bitte wenden Sie sich an einen Administrator.]]></de>
        </locale>
        <locale name="error.password.create" html="true">
            <de><![CDATA[Das Passwort konnte nicht erstellt werden:<br/><br/>[error].]]></de>
        </locale>
        <locale name="success.password.create">
            <de><![CDATA[Das Passwort wurde erfolgreich erstellt.]]></de>
        </locale>
        <locale name="exception.password.setdata.error" html="true">
            <de><![CDATA[Beim Ändern der Daten des Passworts #[passwordId] ist ein Fehler aufgetreten:<br/><br/>[error].]]></de>
        </locale>
        <locale name="exception.password.no.share.rights">
            <de><![CDATA[Das Passwort kann nicht mit anderen Benutzern geteilt werden, da Sie keine Berechtigung haben, Passwörter anderen zugänglich zu machen.]]></de>
        </locale>

        <!-- Class: Handler/Passwords -->
        <locale name="exception.passwords.create.missing.data">
            <de><![CDATA[Es wurde keine Daten für das Password übergeben.]]></de>
        </locale>
        <locale name="exception.passwords.create.no.share.rights">
            <de><![CDATA[Es kann dein anderer Benutzer als Passwort-Eigentümer festgelegt werden, da Sie nicht die nötige Berechtigung besitzen, Passwörter anderen Benutzern zugänglich zu machen.]]></de>
        </locale>

        <!-- Class: CryptoUser -->
        <locale name="exception.cryptouser.not.found">
            <de><![CDATA[Die Session-Daten des Benutzers mit der ID [userId] enthalten nicht die notwendigen Daten, um eine sichere Verschlüsselung zu gewährleisten. Bitte wenden Sie sich an einen Administator]]></de>
        </locale>
        <locale name="exception.cryptouser.no.pw.hash">
            <de><![CDATA[Die Session-Daten des Benutzers mit der ID [userId] enthalten nicht die notwendigen Daten, um eine sichere Verschlüsselung zu gewährleisten. Bitte wenden Sie sich an einen Administator]]></de>
        </locale>
        <locale name="exception.cryptouser.encrypt.no.public.key">
            <de><![CDATA[Der Benutzer mit der ID [userId] hat noch keinen öffentlichen Schlüssel (public key) und kann daher keine Daten verschlüsseln. Der Benutzer muss sich zuerst einloggen und ein gültiges Schlüsselpaar generieren oder hochladen.]]></de>
        </locale>
        <locale name="exception.cryptouser.encrypt.no.private.key">
            <de><![CDATA[Der Benutzer mit der ID [userId] hat noch keinen privaten Schlüssel (private key) und kann daher keine Daten entschlüsseln. Der Benutzer muss sich zuerst einloggen und ein gültiges Schlüsselpaar generieren oder hochladen.]]></de>
        </locale>
        <locale name="exception.cryptouser.encrypt.error">
            <de><![CDATA[Beim verschlüsseln von Daten mit dem öffentlichen Schlüssel des Benutzers mit der ID [userId] ist ein Fehler aufgetreten. Die Daten konnten nicht verschlüsselt werden. Bitt wenden Sie sich an einen Administrator.]]></de>
        </locale>
        <locale name="exception.cryptouser.decrypt.error">
            <de><![CDATA[Beim entschlüsseln von Daten mit dem privaten Schlüssel des Benutzers mit der ID [userId] ist ein Fehler aufgetreten. Die Daten konnten nicht entschlüsselt werden. Bitt wenden Sie sich an einen Administrator.]]></de>
        </locale>
        <locale name="exception.cryptouser.generatekeypair.user.not.logged.in">
            <de><![CDATA[Schlüsselpaar für Benutzer mit der ID [userId] konnte nicht generiert werden. Es wurde versucht, ein Schlüsselpaar für einen anderen Nutzer zu generieren. Nur ein eingeloggter Benutzer selbst kann ein neues Schlüsselpaar für sich setzen.]]></de>
        </locale>
        <locale name="exception.cryptouser.generatekeypair.error">
            <de><![CDATA[Bei der Erstellung eines neuen Schlüsselpaars für den Benutzer mit der ID [userId] ist ein unerwarteter Fehler aufgetreten. Bitte wenden Sie sich an einen Administrator.]]></de>
        </locale>
        <locale name="exception.cryptouser.getpassword.no.right">
            <de><![CDATA[Sie haben kein Zugriffsrecht auf das Passwort mit der ID [passwordId].]]></de>
        </locale>
        <locale name="exception.cryptouser.public.key.not.found">
            <de><![CDATA[Es existiert kein öffentlicher Schlüssel für das Authentifizierungs-Plugin #[authPluginId] für den User #[userId].]]></de>
        </locale>
        <locale name="exception.cryptouser.keypair.not.found">
            <de><![CDATA[Es existiert kein Schlüsselpaar für das Authentifizierungs-Plugin #[authPluginId] für den User #[userId].]]></de>
        </locale>
        <locale name="exception.cryptouser.keypair.not.authentic">
            <de><![CDATA[Das Schlüsselpaar für das Authentifizierungs-Plugin #[authPluginId] für den User #[userId] ist nicht mehr gültig. Bitte kontaktieren Sie umgehend einen Administrator.]]></de>
        </locale>
        <locale name="exception.cryptouser.authkeypair.not.found">
            <de><![CDATA[Der Benutzer #[userId] besitzt kein Schlüsselpaar für das Authentifizierungs-Plugin #[authPluginId].]]></de>
        </locale>
        <locale name="exception.cryptouser.group.access.key.part.not.authentic">
            <de><![CDATA[Ein Teil des Entschlüsselungsschlüssels des Benutzers #[userId] für das Schlüsselpaar der Gruppe #[groupId] hat die Authentizitätsprüfung nicht bestanden und kann daher nicht verwendet werden. Bitte wenden Sie sich an einen Administrator.]]></de>
        </locale>
        <locale name="exception.cryptouser.group.access.key.decrypt.user.has.no.access">
            <de><![CDATA[Das Schlüsselpaar der Gruppe #[groupId] kann nicht durch den Benutzer #[userId] entschlüsselt werden, da der Benutzer keine Zugriffsrecht für diese Gruppe hat.]]></de>
        </locale>
        <locale name="exception.cryptouser.group.access.key.part.auth.key.error" html="true">
            <de><![CDATA[Beim Zugriff auf das Schlüsselpaar einer Authentifizierungs-Methode (#[authKeyPairId]) zur Entschlüsselung des Schlüsselpaars der Gruppe #[groupId] ist ein Fehler aufgetreten:<br/><br/>[error]]]></de>
        </locale>

        <!-- Class: Actors\CryptoGroup -->
        <locale name="exception.cryptogroup.keypair.not.found">
            <de><![CDATA[Der Gruppenschlüssel der Gruppe #[groupId] wurde nicht gefunden. Die Gruppe kann nicht für den Passwort-Manager verwendet werden.]]></de>
        </locale>
        <locale name="exception.cryptogroup.keypair.not.authentic">
            <de><![CDATA[Der Gruppenschlüssel der Gruppe #[groupId] hat die Authentizitätsprüfung nicht bestanden und kann daher nicht verwendet werden. Bitte wenden Sie sich an einen Administrator.]]></de>
        </locale>
        <locale name="exception.cryptogroup.cannot.remove.last.user">
            <de><![CDATA[Der Benutzer #[userId] kann nicht aus der Gruppe #[groupId] entfernt werden, da er der letzte Benutzer ist, der Zugriff auf diese Gruppe hat. Um den Benutzer aus der Gruppe zu entfernen, muss die Gruppe aus Sicherheitsklasse #[securityClassId] entfernt werden.]]></de>
        </locale>
        <locale name="exception.cryptogroup.add.user.not.eligible">
            <de><![CDATA[Der Benutzer #[userId] kann der Gruppe #[groupId] nicht hinzugefügt werden, da er nicht für die benötigte Mindestanzahl an Authentifizierungs-Faktoren der Sicherheitsklasse #[securityClassId] registriert ist.]]></de>
        </locale>
        <locale name="exception.cryptogroup.add.user.general.error">
            <de><![CDATA[Beim Hinzufügen des Benutzers #[userId] zur Gruppe #[groupId] ist ein unerwarteter Fehler aufgetreten. Bitte wenden Sie sich an einen Administrator.]]></de>
        </locale>
        <locale name="exception.cryptogroup.keypair.decryption.authentication.error">
            <de><![CDATA[Der Entschlüsselungsschlüssel der Gruppe #[groupId] kann vom Benutzer #[userId] nicht entschlüsselt werden:<br/><br/>[error].]]></de>
        </locale>
        <locale name="exception.cryptogroup.setsecurityclass.users.not.eligible">
            <de><![CDATA[Die Sicherheitsklasse #[securityClassId] kann der Gruppe #[groupId] nicht zugeordnet werden, da nicht alle Benutzer der Gruppe für die Mindesanzahl an nötigen Authentifizierungs-Faktoren der Sicherheitsklasse registriert sind.]]></de>
        </locale>
        <locale name="exception.cryptogroup.setsecurityclass.users.has.no.group.access">
            <de><![CDATA[Der Benutzer #[userId] kann die Sicherheitsklasse #[securityClassId] der Gruppe #[groupId] nicht zuordnen, da der Benutzer der Gruppe nicht zugewiesen ist.]]></de>
        </locale>

        <!-- Class: Security\Handler\CryptoActors -->
        <locale name="exception.cryptoactors.addcryptogroup.otherwise.associated">
            <de><![CDATA[Es kann kein Schlüsselpaar für die Gruppe #[groupId] erstellt werden, da für die Grupe bereits ein Schlüsselpaar erstellt wurde und diese Gruppe ein .]]></de>
        </locale>
        <locale name="exception.cryptoactors.addcryptogroup.no.users">
            <de><![CDATA[Die Gruppe #[groupId] kann der Sicherheitsklasse #[securityClassId] nicht zugeordnet werden, da die Gruppe keine Benutzer hat. Eine Gruppe muss mindestens einen Benutzer haben, bevor sie einer Sicherheitsklasse zugeordnet werden kann.]]></de>
        </locale>
        <locale name="exception.cryptoactors.addcryptogroup.users.not.eligible">
            <de><![CDATA[Die Gruppe #[groupId] kann der Sicherheitsklasse #[securityClassId] nicht zugeordnet werden, da nicht alle Benutzer der Gruppe für die Mindestanzahl der nötigen Authentifizierungs-Faktoren der Sicherheitsklasse registriert sind.]]></de>
        </locale>
        <locale name="exception.cryptoactors.addcryptogroup.group.already.exists">
            <de><![CDATA[Die Gruppe #]]></de>
        </locale>

        <!-- Class: Security\Authentication\Plugin -->
        <locale name="exception.authentication.plugin.register.error">
            <de><![CDATA[Die Authentifizierungsinformationen sind ungültig.]]></de>
        </locale>
        <locale name="exception.auth.plugin.register.database.error">
            <de><![CDATA[Bei der Registrierung ist ein unerwarteter Fehler aufgetreten. Bitte kontaktieren Sie einen Administrator.]]></de>
        </locale>
        <locale name="exception.auth.plugin.derived.key.error">
            <de><![CDATA[Die Ableitung des Schlüssel aus Authentifizierungsinformationen für das Authentifizierungs-Plugin #[pluginId] schlug fehl:<br/><br/>[error].]]></de>
        </locale>

        <!-- Class: Security\Handler\Authentication -->
        <locale name="exception.authentication.authenticate.error" html="true">
            <de><![CDATA[Der Authentifizierungs-Vorgang war nicht erfolgreich:<br/><br/>[error]<br/><br/>Bitte versuchen Sie es erneut.]]></de>
        </locale>
        <locale name="exception.auth.plugin.not.found">
            <de><![CDATA[Das Authentifizierungs-Plugin mit der ID [id] wurde nicht gefunden.]]></de>
        </locale>

        <!-- Ajax -->
        <locale name="success.auth.registeruser">
            <de><![CDATA[Die Registrierung für dieses Authentifizierungs-Plugin war erfolgreich. Sie können nun Passwörter erstellen und auf Passwörter zugreifen, die diese Authentifizierungs-Methode erfordern.]]></de>
        </locale>
        <locale name="error.auth.registeruser">
            <de><![CDATA[Die Registrierung für dieses Authentifizierungs-Plugin war nicht erfolgreich:<br/><br/>[error]]]></de>
        </locale>
        <locale name="error.auth.changeauth">
            <de><![CDATA[Die Änderung von Authentifizierungsinformationen für dieses Authentifizierungs-Plugin war nicht erfolgreich:<br/><br/>[error]]]></de>
        </locale>
        <locale name="success.auth.changeauth">
            <de><![CDATA[Die Änderung von Authentifizierungsinformationen für dieses Authentifizierungs-Plugin war erfolgreich.]]></de>
        </locale>
        <locale name="error.auth.changeauth">
            <de><![CDATA[Die Änderung von Authentifizierungsinformationen für dieses Authentifizierungs-Plugin war nicht erfolgreich:<br/><br/>[error]]]></de>
        </locale>
        <locale name="error.password.edit">
            <de><![CDATA[Die Änderung der Passwort-Daten (#[passwordId]) war nicht erfolgreich:<br/><br/>[error]]]></de>
        </locale>
        <locale name="success.password.edit">
            <de><![CDATA[Die Passwort-Daten (#[passwordId]) wurden erfolgreich geändert.]]></de>
        </locale>
        <locale name="error.password.share">
            <de><![CDATA[Das Teilen der Passwort-Daten (#[passwordId]) war nicht erfolgreich:<br/><br/>[error]]]></de>
        </locale>
        <locale name="success.password.share">
            <de><![CDATA[Die Passwort-Daten (#[passwordId]) wurden erfolgreich mit den festgelegten Benutzern und Gruppen geteilt.]]></de>
        </locale>
        <locale name="error.password.delete">
            <de><![CDATA[Das Löschen des Passworts (#[passwordId]) war nicht erfolgreich:<br/><br/>[error]]]></de>
        </locale>
        <locale name="success.password.delete">
            <de><![CDATA[Das Passwort (#[passwordId]) wurde erfolgreich gelöscht.]]></de>
        </locale>

        <!-- System -->
        <locale name="exception.system.auth.key.file.not.found">
            <de><![CDATA[Authentifizierungs-Schlüssel des Systems nicht gefunden.]]></de>
        </locale>

        <!-- Class: Security\Authentication\SecurityClass -->
        <locale name="exception.securityclass.authenticate.missing.authdata">
            <de><![CDATA[Die Authentifizierungsinformationen für das Authentifizierungs-Plugin "[authPluginTitle]" #[authPluginId] wurden nicht übergeben.]]></de>
        </locale>
        <locale name="exception.securityclass.authenticate.authdata.not.given">
            <de><![CDATA[Die Authentifizierungsinformationen wurden nicht übergeben.]]></de>
        </locale>
        <locale name="attention.securityclass.edit.groups.cannot.delete.group">
            <de><![CDATA[Die Gruppe #[groupId] kann nicht aus der Sicherheitsklasse #[securityClassId] entfernt werden. Gruppen können nur aus einer Sicherheitsklasse entfernt werden, wenn sie einer anderen Sicherheitsklasse zugeordnet oder direkt gelöscht werden.]]></de>
        </locale>

        <!-- Class: Security\Keys\AuthKeyPair -->
        <locale name="exception.authkeypair.not.found">
            <de><![CDATA[Das Schlüsselpaar #[id] wurde nicht gefunden.]]></de>
        </locale>
        <locale name="exception.authkeypair.not.authentic">
            <de><![CDATA[Das Schlüsselpaar #[id] hat die Authentizitätsprüfung nicht bestanden und kann daher nicht verwendet werden. Bitte wenden Sie sich an einen Administrator.]]></de>
        </locale>

        <!-- Events -->
        <locale name="attention.events.onusersavebegin.remove.user.error">
            <de><![CDATA[Der Benutzer #[userId] konnte aus der Gruppe #[groupId] nicht entfernt werden:<br/><br/>[error].]]></de>
        </locale>
        <locale name="attention.events.onusersavebegin.add.user.error">
            <de><![CDATA[Der Benutzer #[userId] konnte der Gruppe #[groupId] nicht zugeordnet werden:<br/><br/>[error].]]></de>
        </locale>

    </groups>

    <groups name="pcsg/grouppasswordmanager" datatype="php,js">

        <locale name="menu.apps.gpm.title">
            <de><![CDATA[Passwort-Manager]]></de>
        </locale>
        <locale name="menu.extras.gpm.title">
            <de><![CDATA[Passwort-Manager]]></de>
        </locale>
        <locale name="menu.extras.gpm.auth.title">
            <de><![CDATA[Authentifizierung]]></de>
        </locale>
        <locale name="menu.extras.gpm.securityclasses.title">
            <de><![CDATA[Sicherheitsklassen]]></de>
        </locale>
        <locale name="menu.extras.gpm.groups.title">
            <de><![CDATA[Passwort-Gruppen]]></de>
        </locale>

    </groups>

    <groups name="pcsg/grouppasswordmanager" datatype="js">

        <!-- Control: passwords/Panel -->
        <locale name="passwords.panel.title">
            <de><![CDATA[Passwort-Manager]]></de>
        </locale>
        <locale name="controls.gpm.passwordlist.btn.add">
            <de><![CDATA[Neues Passwort]]></de>
        </locale>
        <locale name="controls.gpm.passwords.panel.tbl.header.title">
            <de><![CDATA[Titel]]></de>
        </locale>
        <locale name="controls.gpm.passwords.panel.tbl.header.description">
            <de><![CDATA[Kurzbeschreibung]]></de>
        </locale>
        <locale name="controls.gpm.passwords.panel.tbl.header.datatype">
            <de><![CDATA[Typ]]></de>
        </locale>
        <locale name="gpm.passwords.panel.create.title">
            <de><![CDATA[Neues Passwort erstellen]]></de>
        </locale>
        <locale name="controls.gpm.passwords.btn.add">
            <de><![CDATA[Neues Passwort]]></de>
        </locale>
        <locale name="controls.gpm.passwords.btn.view">
            <de><![CDATA[Passwort ansehen]]></de>
        </locale>
        <locale name="controls.gpm.passwords.btn.share">
            <de><![CDATA[Passwort teilen]]></de>
        </locale>
        <locale name="controls.gpm.passwords.btn.edit">
            <de><![CDATA[Passwort bearbeiten]]></de>
        </locale>
        <locale name="controls.gpm.passwords.btn.delete">
            <de><![CDATA[Passwort löschen]]></de>
        </locale>
        <locale name="controls.gpm.passwords.btn.searchremove">
            <de><![CDATA[Suchfilter entfernen]]></de>
        </locale>
        <locale name="gpm.passwords.panel.delete.popup.title">
            <de><![CDATA[Passwort löschen]]></de>
        </locale>
        <locale name="gpm.passwords.panel.delete.popup.info.title">
            <de><![CDATA[Passwort löschen]]></de>
        </locale>
        <locale name="gpm.passwords.panel.delete.popup.info.description" html="true">
            <de><![CDATA[Sind Sie sicher, dass sie das Passwort <b>[passwordTitle]</b> mit der ID <b>[passwordId]</b> unwiderruflich löschen wollen?]]></de>
        </locale>
        <locale name="gpm.passwords.panel.delete.popup.btn.text">
            <de><![CDATA[Löschen]]></de>
        </locale>
        <locale name="gpm.passwords.panel.delete.popup.btn">
            <de><![CDATA[Hier klicken, um das Passwort unwiderruflich zu löschen]]></de>
        </locale>
        <locale name="gpm.passwords.panel.view.title">
            <de><![CDATA[Passwort ansehen]]></de>
        </locale>
        <locale name="gpm.passwords.panel.share.title">
            <de><![CDATA[Passwort teilen]]></de>
        </locale>
        <locale name="gpm.passwords.panel.edit.title">
            <de><![CDATA[Passwort bearbeiten]]></de>
        </locale>
        <locale name="gpm.passwords.panel.search.title">
            <de><![CDATA[Passwort-Suche]]></de>
        </locale>


        <!-- Control: password/Create -->
        <locale name="password.create.template.title">
            <de><![CDATA[Neues Passwort erstellen]]></de>
        </locale>
        <locale name="password.create.template.basicData">
            <de><![CDATA[Stammdaten]]></de>
        </locale>
        <locale name="password.create.template.securityClass">
            <de><![CDATA[Sicherheitsklasse]]></de>
        </locale>
        <locale name="password.create.template.passwordTitle">
            <de><![CDATA[Titel]]></de>
        </locale>
        <locale name="password.create.template.passwordDescription">
            <de><![CDATA[Beschreibung]]></de>
        </locale>
        <locale name="password.create.template.payload">
            <de><![CDATA[Inhalt]]></de>
        </locale>
        <locale name="password.create.template.passwordPayload">
            <de><![CDATA[Passwort-Inhalt]]></de>
        </locale>
        <locale name="password.create.template.payloadWarning">
            <de><![CDATA[Achtung! Dies sind die Daten, die verschlüsselt werden und auf die nach der Erstellung ausschließlich Berechtigte zugreifen können!]]></de>
        </locale>
        <locale name="password.create.template.owner">
            <de><![CDATA[Eigentümer]]></de>
        </locale>
        <locale name="password.create.template.passwordOwner">
            <de><![CDATA[Benutzer / Gruppe]]></de>
        </locale>
        <locale name="password.create.submit.no.owner.assigned">
            <de><![CDATA[Bitte legen Sie einen Benutzer oder eine Gruppe als Passwort-Eigentümer fest.]]></de>
        </locale>

        <!-- Control: password/Edit -->
        <locale name="edit.template.title">
            <de><![CDATA[Passwort bearbeiten]]></de>
        </locale>

        <!-- Control: auth/Panel -->
        <locale name="auth.panel.btn.register">
            <de><![CDATA[Registrieren]]></de>
        </locale>
        <locale name="auth.panel.btn.change">
            <de><![CDATA[Registrierungsinformationen ändern]]></de>
        </locale>
        <locale name="auth.panel.tbl.header.registered">
            <de><![CDATA[registriert]]></de>
        </locale>
        <locale name="auth.panel.tbl.header.title">
            <de><![CDATA[Titel]]></de>
        </locale>
        <locale name="auth.panel.tbl.header.description">
            <de><![CDATA[Beschreibung]]></de>
        </locale>
        <locale name="auth.panel.registered.yes">
            <de><![CDATA[ja]]></de>
        </locale>
        <locale name="auth.panel.registered.no">
            <de><![CDATA[nein]]></de>
        </locale>
        <locale name="auth.panel.register.btn.register">
            <de><![CDATA[Registrieren]]></de>
        </locale>
        <locale name="auth.panel.change.btn.register">
            <de><![CDATA[Bestätigen]]></de>
        </locale>
        <locale name="gpm.auth.panel.change.title">
            <de><![CDATA[Authentifizierungsinformationen ändern]]></de>
        </locale>
        <locale name="auth.panel.register.btn.register">
            <de><![CDATA[Neue Informationen senden]]></de>
        </locale>

        <!-- Control: auth/Register -->
        <locale name="auth.template.title">
            <de><![CDATA[Registrierung für eine Authentifizierungsmethode]]></de>
        </locale>
        <locale name="auth.template.basicData">
            <de><![CDATA[Eingabe der Authentifizierungsinformationen]]></de>
        </locale>

        <!-- Control: auth/Change -->
        <locale name="auth.change.template.title">
            <de><![CDATA[Änderung der Authentifizierungsinformationen für ein Authentifizierungs-Methode]]></de>
        </locale>
        <locale name="auth.change.template.basicData">
            <de><![CDATA[Eingabe der Authentifizierungsinformationen]]></de>
        </locale>

        <!-- Control: auth/EligibleActorSelect -->
        <locale name="controls.eligibleactorselect.switch.groups.btn">
            <de><![CDATA[Hier klicken, um alle Gruppen anzuzeigen, die als Passwort-Eigentümer oder -Empfänger in Frage kommen]]></de>
        </locale>
        <locale name="controls.eligibleactorselect.switch.users.btn">
            <de><![CDATA[Hier klicken, um alle Benutzer anzuzeigen, die als Passwort-Eigentümer oder -Empfänger in Frage kommen]]></de>
        </locale>

        <!-- Control: auth/Authenticate -->
        <locale name="controls.authenticate.popup.title">
            <de><![CDATA[Authentifizierung]]></de>
        </locale>
        <locale name="controls.authenticate.popup.info.title">
            <de><![CDATA[Authentifizierung erforderlich!]]></de>
        </locale>
        <locale name="controls.authenticate.popup.info.description" html="true">
            <de><![CDATA[Für diese Operation ist eine Authentifizierung für die Sicherheitsklasse <b>[securityClass]</b> erforderlich. Bitte authentifzieren Sie sich bei <b>mindestens [requiredFactors]</b> dafür nötigen Authentifizierungs-Plugins.]]></de>
        </locale>
        <locale name="controls.authenticate.popup.btn.text">
            <de><![CDATA[Authentifizieren]]></de>
        </locale>
        <locale name="controls.authenticate.popup.btn">
            <de><![CDATA[Hier klicken, um die Authentifizierung durchzuführen]]></de>
        </locale>
        <locale name="controls.authenticate.popup.btn.abort.text">
            <de><![CDATA[Abbrechen]]></de>
        </locale>
        <locale name="controls.authenticate.popup.btn.abort">
            <de><![CDATA[Hier klicken, um den Authentifizierungsvorgang abzubrechen]]></de>
        </locale>

        <!-- Control: passwords/View -->
        <locale name="controls.password.view.popup.title">
            <de><![CDATA[Passwort ansehen]]></de>
        </locale>

        <!-- Control: password/Panel -->
        <locale name="gpm.password.btn.save.text">
            <de><![CDATA[Speichern]]></de>
        </locale>
        <locale name="gpm.password.panel.btn.edit">
            <de><![CDATA[Passwort-Daten bearbeiten]]></de>
        </locale>
        <locale name="gpm.password.panel.btn.share">
            <de><![CDATA[Passwort-Daten teilen]]></de>
        </locale>

        <!-- Control: securityclasses/Panel -->
        <locale name="securityclasses.panel.btn.add">
            <de><![CDATA[Sicherheitsklasse anlegen]]></de>
        </locale>
        <locale name="securityclasses.panel.btn.edit">
            <de><![CDATA[Sicherheitsklasse bearbeiten]]></de>
        </locale>
        <locale name="securityclasses.panel.btn.delete">
            <de><![CDATA[Sicherheitsklasse löschen]]></de>
        </locale>
        <locale name="securityclasses.panel.tbl.header.description">
            <de><![CDATA[Beschreibung]]></de>
        </locale>
        <locale name="securityclasses.panel.tbl.header.title">
            <de><![CDATA[Titel]]></de>
        </locale>
        <locale name="securityclasses.panel.tbl.header.factors">
            <de><![CDATA[Authentifizierungs-Faktoren]]></de>
        </locale>
        <locale name="gpm.securityclasses.panel.create.title">
            <de><![CDATA[Neue Sicherheitsklasse anlegen]]></de>
        </locale>
        <locale name="gpm.securityclasses.panel.edit.title">
            <de><![CDATA[Sicherheitsklasse bearbeiten]]></de>
        </locale>
        <locale name="gpm.securityclasses.panel.delete.popup.info.description" html="true">
            <de><![CDATA[Sind Sie sicher, dass Sie die Sicherheitsklasse <b>[securityClassTitle]</b> (#[securityClassId]) unwiderruflich löschen wollen?<br/>Bitte beachten Sie, dass eine Löschung nur möglich ist, wenn aktuell keine Passwörter angelegt sind, der diese Sicherheitsklasse zugeordnet ist.]]></de>
        </locale>
        <locale name="gpm.securityclasses.panel.delete.popup.info.title">
            <de><![CDATA[Sicherheitsklasse löschen]]></de>
        </locale>
        <locale name="gpm.securityclasses.panel.delete.popup.btn.text">
            <de><![CDATA[Löschen]]></de>
        </locale>
        <locale name="gpm.securityclasses.panel.delete.popup.btn">
            <de><![CDATA[Hier klicken, um die gewählte Sicherheitsklasse unwiderruflich zu löschen]]></de>
        </locale>
        <locale name="gpm.passwords.panel.search.title">
            <de><![CDATA[Passwort-Suche]]></de>
        </locale>
        <locale name="gpm.passwords.panel.btn.search">
            <de><![CDATA[Suche starten]]></de>
        </locale>

        <!-- Control: securityclasses/Create -->
        <locale name="securityclasses.create.template.createtitle">
            <de><![CDATA[Neue Sicherheitsklasse anlegen]]></de>
        </locale>
        <locale name="securityclasses.create.template.title">
            <de><![CDATA[Titel]]></de>
        </locale>
        <locale name="securityclasses.create.template.description">
            <de><![CDATA[Beschreibung]]></de>
        </locale>
        <locale name="securityclasses.create.template.authPlugins">
            <de><![CDATA[Auth.-Faktoren]]></de>
        </locale>
        <locale name="securityclasses.create.template.requiredFactors">
            <de><![CDATA[Mindestens benötigte Faktoren]]></de>
        </locale>
        <locale name="securityclasses.create.template.authPluginsWarning" html="true">
            <de><![CDATA[<b>Hinweis:</b> Die festgelegten Authentifizierungs-Faktoren können nach der Erstellung der Sicherheitsklasse nicht mehr geändert werden.]]></de>
        </locale>
        <locale name="securityclasses.create.template.groups">
            <de><![CDATA[Gruppen]]></de>
        </locale>
        <locale name="securityclasses.create.template.groupsInfo">
            <de><![CDATA[Die Gruppen für eine Sicherheitsklasse können festgelegt werden, nachdem die Sicherheitsklasse erstellt wurde.]]></de>
        </locale>

        <!-- Control: securityclasses/Edit -->
        <locale name="securityclasses.edit.template.edittitle">
            <de><![CDATA[Sicherheitsklasse bearbeiten]]></de>
        </locale>
        <locale name="securityclasses.edit.template.title">
            <de><![CDATA[Titel]]></de>
        </locale>
        <locale name="securityclasses.edit.template.description">
            <de><![CDATA[Beschreibung]]></de>
        </locale>
        <locale name="securityclasses.edit.template.authPlugins">
            <de><![CDATA[Auth.-Faktoren]]></de>
        </locale>
        <locale name="securityclasses.edit.template.groups">
            <de><![CDATA[Gruppen]]></de>
        </locale>
        <locale name="securityclasses.edit.template.requiredFactors">
            <de><![CDATA[Mindestens benötigte Faktoren]]></de>
        </locale>

        <!-- Control: password/Share -->
        <locale name="controls.password.share.title">
            <de><![CDATA[Passwort teilen]]></de>
        </locale>
        <locale name="controls.password.share.info" html="true">
            <de><![CDATA[Hier kann festgelegt werden, welche Benutzer und Gruppen die Berechtigung haben, dass Passwort <b>[passwordTitle] (#[passwordId])</b> anzusehen.]]></de>
        </locale>
        <locale name="controls.password.share.users.header">
            <de><![CDATA[Benutzer]]></de>
        </locale>
        <locale name="controls.password.share.groups.header">
            <de><![CDATA[Gruppen]]></de>
        </locale>

        <!-- Control: actors/Select -->
        <locale name="actors.select.placeholder.users">
            <de><![CDATA[Nach geeigneten Benutzern suchen]]></de>
        </locale>
        <locale name="actors.select.placeholder.groups">
            <de><![CDATA[Nach geeigneten Gruppen suchen]]></de>
        </locale>
        <locale name="actors.select.placeholder.both">
            <de><![CDATA[Nach geeigneten Benutzern und Gruppen suchen]]></de>
        </locale>

        <!-- Control: passwordtypes/Select -->
        <locale name="passwordtypes.select.type.FTP">
            <de><![CDATA[FTP-Server]]></de>
        </locale>
        <locale name="passwordtypes.select.type.Login">
            <de><![CDATA[Login-Daten]]></de>
        </locale>

        <!-- Control: passwordtypes/FTP -->
        <locale name="password.types.ftp.template.title">
            <de><![CDATA[FTP-Daten]]></de>
        </locale>
        <locale name="password.types.ftp.template.host">
            <de><![CDATA[Host]]></de>
        </locale>
        <locale name="password.types.ftp.template.user">
            <de><![CDATA[Benutzer]]></de>
        </locale>
        <locale name="password.types.ftp.template.password">
            <de><![CDATA[Passwort]]></de>
        </locale>
        <locale name="password.types.ftp.template.note">
            <de><![CDATA[Notiz]]></de>
        </locale>
        <locale name="password.types.login.template.title">
            <de><![CDATA[Login-Daten]]></de>
        </locale>
        <locale name="password.types.login.template.user">
            <de><![CDATA[Benutzer]]></de>
        </locale>
        <locale name="password.types.login.template.password">
            <de><![CDATA[Passwort]]></de>
        </locale>
        <locale name="password.types.login.template.note">
            <de><![CDATA[Notiz]]></de>
        </locale>

        <!-- Control: passwords/Search -->
        <locale name="password.search.template.title">
            <de><![CDATA[Passwort-Suche]]></de>
        </locale>
        <locale name="password.search.template.searchData">
            <de><![CDATA[Such-Angaben]]></de>
        </locale>
        <locale name="password.search.template.searchterm">
            <de><![CDATA[Suchbegriff]]></de>
        </locale>
        <locale name="password.search.template.searchfields">
            <de><![CDATA[Durchsuchte Felder]]></de>
        </locale>
        <locale name="password.search.template.passwordTypes">
            <de><![CDATA[Passwort-Typen]]></de>
        </locale>
        <locale name="password.search.template.passwordTypesOptionAll">
            <de><![CDATA[Alle Typen]]></de>
        </locale>
        <locale name="password.search.template.searchfieldsTitle">
            <de><![CDATA[Titel]]></de>
        </locale>
        <locale name="password.search.template.searchfieldsDescription">
            <de><![CDATA[Kurzbeschreibung]]></de>
        </locale>

        <!-- Control: password/View -->
        <locale name="password.view.restricted.info">
            <de><![CDATA[Sie müssen sich zuerst authentifizieren, bevor Passwort-Daten angezeigt werden können.]]></de>
        </locale>

        <!-- Control: actors/GroupEdit -->
        <locale name="gpm.groups.panel.edit.title">
            <de><![CDATA[Passwort-Gruppe bearbeiten]]></de>
        </locale>
        <locale name="actors.groups.edit.template.title">
            <de><![CDATA[Passwort-Gruppe bearbeiten]]></de>
        </locale>
        <locale name="actors.groups.edit.template.basicData">
            <de><![CDATA[Sicherheitsklasse]]></de>
        </locale>
        <locale name="actors.groups.edit.template.securityclass">
            <de><![CDATA[Zugeordnete Sicherheitsklasse]]></de>
        </locale>
        <locale name="controls.groupedit.no.securityclass">
            <de><![CDATA[Die Gruppe ist noch keiner Sicherheitsklasse zugeordnet. Weisen Sie der Gruppe eine Sicherheitsklasse zu, damit sie im Rahmen des Passwort-Managers verwendet werden kann.]]></de>
        </locale>
        <locale name="controls.groupedit.not.in.group">
            <de><![CDATA[Sie können die Sicherheitsklasse dieser Gruppe nicht ändern, da Sie dieser Gruppe nicht zugewiesen sind.]]></de>
        </locale>
    </groups>

</locales>